poemail/__init__.py
poemail/api/__init__.py
poemail/api/base.py
poemail/api/receive.py
poemail/api/send.py
poemail/core/BaseEmail.py
poemail/core/ReceiveEmail.py
poemail/core/SendEmail.py
poemail/core/__init__.py
poemail/lib/Const.py
poemail/lib/__init__.py
tests/__init__.py
tests/test_email.py
poemail-0.0.4.dist-info/LICENSE
poemail-0.0.4.dist-info/METADATA
poemail-0.0.4.dist-info/WHEEL
poemail-0.0.4.dist-info/top_level.txt
poemail-0.0.4.dist-info/RECORD
