Metadata-Version: 2.1
Name: poemail
Version: 0.0.4
Summary: pip install poemail
Home-page: https://www.python-office.com/course-002/poemail/poemail.html
Author: CoderWanFeng
Author-email: 1957875073@qq.com
License: MIT
Project-URL: Bug Tracker, https://github.com/CoderWanFeng/poemail/issues
Project-URL: Documentation, https://github.com/CoderWanFeng/poemail/blob/main/README.md
Project-URL: Source Code, https://github.com/CoderWanFeng/poemail
Platform: any
Requires-Python: >=3.7
License-File: LICENSE
Requires-Dist: PyEmail
Requires-Dist: Deprecated
Requires-Dist: pofile
Requires-Dist: pocode
